visionedgefusion/__init__.py
visionedgefusion/v1/__init__.py
visionedgefusion/v1/core.py
visionedgefusion-1.0.0.dist-info/METADATA
visionedgefusion-1.0.0.dist-info/WHEEL
visionedgefusion-1.0.0.dist-info/top_level.txt
visionedgefusion-1.0.0.dist-info/RECORD
