Metadata-Version: 2.4
Name: visionedgefusion
Version: 1.0.0
Summary: A lightweight and educational Python toolkit for fundamental feature extraction using Difference of Gaussians (DoG) and Histogram of Oriented Gradients (HoG).
Author-email: Abhipushp Maurya <abhipushp1765408.bov@gmail.com>
License: MIT
Classifier: Programming Language :: Python :: 3
Classifier: Operating System :: OS Independent
Classifier: Intended Audience :: Developers
Classifier: Intended Audience :: Education
Classifier: Intended Audience :: Science/Research
Classifier: Topic :: Scientific/Engineering :: Image Processing
Classifier: Topic :: Software Development :: Libraries :: Python Modules
Requires-Python: >=3.8
Requires-Dist: numpy
Requires-Dist: opencv-python-headless
Requires-Dist: scikit-image
Requires-Dist: scipy
